EasyPySqlite/__init__.py
EasyPySqlite-0.0.4.dist-info/METADATA
EasyPySqlite-0.0.4.dist-info/WHEEL
EasyPySqlite-0.0.4.dist-info/top_level.txt
EasyPySqlite-0.0.4.dist-info/RECORD
